perfreport/__init__.py
perfreport/__main__.py
perfreport/__version__.py
perfreport-0.0.0.dist-info/LICENSE
perfreport-0.0.0.dist-info/METADATA
perfreport-0.0.0.dist-info/WHEEL
perfreport-0.0.0.dist-info/top_level.txt
perfreport-0.0.0.dist-info/RECORD
