Metadata-Version: 2.2
Name: perfreport
Version: 0.0.0
Summary: A performance measurement tool for databases and various systems. It benchmarks performance, generates detailed reports with charts, and exports them in HTML and Markdown formats.
Author-email: mor <whiteluna@gmail.com>
License: MIT License
Project-URL: Homepage, https://github.com/whiteluna/perfreport
Project-URL: Issues, https://github.com/whiteluna/perfreport/issues
Classifier: Programming Language :: Python :: 3
Classifier: Operating System :: OS Independent
Requires-Python: >=3.8
License-File: LICENSE
